tymon/__init__.py
tymon/assistant/__init__.py
tymon/assistant/assistant.py
tymon/assistant/data_operator.py
tymon/assistant/model_operator.py
tymon/assistant/time_series/__init__.py
tymon/assistant/time_series/time_series_assistant.py
tymon/assistant/time_series/ts_data_operator.py
tymon/assistant/time_series/ts_model_operator.py
tymon/model_hub/__init__.py
tymon/model_hub/time_series/__init__.py
tymon/model_hub/time_series/lstm.py
tymon/tools/__init__.py
tymon/tools/para_gui.py
tymon-0.0.4.dist-info/LICENSE
tymon-0.0.4.dist-info/METADATA
tymon-0.0.4.dist-info/WHEEL
tymon-0.0.4.dist-info/top_level.txt
tymon-0.0.4.dist-info/RECORD
