Metadata-Version: 2.1
Name: tymon
Version: 0.0.4
Summary: An AI Assistant More Than a Toolkit
Home-page: https://github.com/TymonXie/tymon
Author: TymonXie
Author-email: 847250484@qq.com
License: UNKNOWN
Platform: UNKNOWN
Classifier: Programming Language :: Python :: 3.6
Classifier: Programming Language :: Python :: 3.7
Requires-Python: ~=3.6
License-File: LICENSE
Requires-Dist: scikit-learn (>=0.24.2)
Requires-Dist: torch (>=1.9.0)
Requires-Dist: pandas (>=1.1.5)
Requires-Dist: numpy (>=1.19)
Requires-Dist: matplotlib (>=3.3.4)
